setup.py
distributions/Binomialdistribution.py
distributions/Gaussiandistribution.py
distributions/Generaldistribution.py
distributions/__init__.py
gallant_distributions.egg-info/PKG-INFO
gallant_distributions.egg-info/SOURCES.txt
gallant_distributions.egg-info/dependency_links.txt
gallant_distributions.egg-info/not-zip-safe
gallant_distributions.egg-info/top_level.txt