Metadata-Version: 1.0
Name: gallant-distributions
Version: 0.1
Summary: Gaussian distributions
Home-page: UNKNOWN
Author: gallant decoy
Author-email: gallantdecoy@gmail.com
License: UNKNOWN
Platform: UNKNOWN
